KluchinskiySerializator/__init__.py
KluchinskiySerializator/consts_for_function.py
KluchinskiySerializator/great_serializer.py
KluchinskiySerializator/my_json_serializer.py
KluchinskiySerializator/my_xml_serializer.py
KluchinskiySerializator/python_serializer.py
KluchinskiySerializator-2.0.dist-info/METADATA
KluchinskiySerializator-2.0.dist-info/WHEEL
KluchinskiySerializator-2.0.dist-info/top_level.txt
KluchinskiySerializator-2.0.dist-info/RECORD
