Metadata-Version: 2.1
Name: KluchinskiySerializator
Version: 2.0
Summary: Release library
Author: Vladimir Kluchinskiy
Author-email: vova.klyuch@gmail.com
License: MIT
Classifier: Intended Audience :: Developers
Classifier: License :: OSI Approved :: MIT License
Classifier: Programming Language :: Python
Classifier: Programming Language :: Python :: 3
Classifier: Programming Language :: Python :: 3.9
Classifier: Programming Language :: Python :: 3.10
Classifier: Programming Language :: Python :: 3.11
Classifier: Operating System :: OS Independent
Requires-Dist: regex
